microscope.py
django_microscope-0.1.1.dist-info/LICENSE
django_microscope-0.1.1.dist-info/METADATA
django_microscope-0.1.1.dist-info/WHEEL
django_microscope-0.1.1.dist-info/top_level.txt
django_microscope-0.1.1.dist-info/RECORD
