Metadata-Version: 2.1
Name: django-microscope
Version: 0.1.1
Summary: Turn a Django app into a Django project so it can run as a microservice or whatever
Home-page: https://github.com/kezabelle/django-microscope/
Author: Keryn Knight
Author-email: django-microscope@kerynknight.com
Maintainer: Keryn Knight
Maintainer-email: django-microscope@kerynknight.com
License: BSD License
Keywords: django django-microscope manage.py microservice microscope
Platform: UNKNOWN
Classifier: Development Status :: 3 - Alpha
Classifier: Intended Audience :: Developers
Classifier: License :: OSI Approved :: BSD License
Classifier: Natural Language :: English
Classifier: Programming Language :: Python :: 2.7
Classifier: Programming Language :: Python :: 3
Classifier: Framework :: Django
Requires-Dist: Django (>=1.9)
Requires-Dist: django-environ (>=0.4.4)
